AUTHORS
CHANGELOG
LICENSE
MANIFEST.in
README.rst
setup.py
cmsplugin_rst/__init__.py
cmsplugin_rst/cms_plugins.py
cmsplugin_rst/docutils_plugins.py
cmsplugin_rst/forms.py
cmsplugin_rst/models.py
cmsplugin_rst/utils.py
cmsplugin_rst.egg-info/PKG-INFO
cmsplugin_rst.egg-info/SOURCES.txt
cmsplugin_rst.egg-info/dependency_links.txt
cmsplugin_rst.egg-info/not-zip-safe
cmsplugin_rst.egg-info/requires.txt
cmsplugin_rst.egg-info/top_level.txt
cmsplugin_rst/migrations/0001_initial.py
cmsplugin_rst/migrations/0002_rstpluginmodel_header_level.py
cmsplugin_rst/migrations/__init__.py